StellarPy-0.5a0.dist-info/DESCRIPTION.rst
StellarPy-0.5a0.dist-info/METADATA
StellarPy-0.5a0.dist-info/RECORD
StellarPy-0.5a0.dist-info/WHEEL
StellarPy-0.5a0.dist-info/metadata.json
StellarPy-0.5a0.dist-info/top_level.txt
stellarpy/__init__.py
stellarpy/core.py
stellarpy/make.py
stellarpy/test.py
