Metadata-Version: 2.0
Name: StellarPy
Version: 0.5a0
Summary: Python Planetary System
Home-page: https://github.com/ezinall/SolPy
Author: Ruslan Vasilevskiy
Author-email: vasilevskiy.r@gmail.com
License: BSD
Keywords: space,plot,science
Platform: any
Classifier: Development Status :: 3 - Alpha
Classifier: Intended Audience :: Developers
Classifier: Intended Audience :: Science/Research
Classifier: Topic :: Scientific/Engineering
Classifier: Topic :: Software Development
Classifier: License :: OSI Approved :: BSD License
Classifier: Programming Language :: Python :: 3
Classifier: Programming Language :: Python :: 3.4
Classifier: Programming Language :: Python :: 3.5
Classifier: Programming Language :: Python :: 3.6
Requires-Python: ==3, >=3.4
Requires-Dist: numpy (>=1.13.3)
Requires-Dist: pyqtgraph (>=0.10.0)
